<annotation>
  <folder>VOC2007</folder>
  <filename>000364.jpg</filename>
  <size>
    <width>1080</width>
    <height>1920</height>
    <depth>3</depth>
  </size>
  <object>
    <name>FrameLayout</name>
    <pose>Unspecified</pose>
    <truncated>0</truncated>
    <difficult>0</difficult>
    <bndbox>
      <xmin>188</xmin>
      <ymin>63</ymin>
      <xmax>1080</xmax>
      <ymax>1794</ymax>
    </bndbox>
  </object>
  <object>
    <name>LinearLayout</name>
    <pose>Unspecified</pose>
    <truncated>0</truncated>
    <difficult>0</difficult>
    <bndbox>
      <xmin>188</xmin>
      <ymin>63</ymin>
      <xmax>1080</xmax>
      <ymax>1794</ymax>
    </bndbox>
  </object>
  <object>
    <name>LinearLayout</name>
    <pose>Unspecified</pose>
    <truncated>0</truncated>
    <difficult>0</difficult>
    <bndbox>
      <xmin>188</xmin>
      <ymin>63</ymin>
      <xmax>1080</xmax>
      <ymax>1794</ymax>
    </bndbox>
  </object>
  <object>
    <name>View</name>
    <pose>Unspecified</pose>
    <truncated>0</truncated>
    <difficult>0</difficult>
    <bndbox>
      <xmin>188</xmin>
      <ymin>63</ymin>
      <xmax>1080</xmax>
      <ymax>210</ymax>
    </bndbox>
  </object>
  <object>
    <name>ImageView</name>
    <pose>Unspecified</pose>
    <truncated>0</truncated>
    <difficult>0</difficult>
    <bndbox>
      <xmin>188</xmin>
      <ymin>63</ymin>
      <xmax>1080</xmax>
      <ymax>210</ymax>
    </bndbox>
  </object>
  <object>
    <name>ImageView</name>
    <pose>Unspecified</pose>
    <truncated>0</truncated>
    <difficult>0</difficult>
    <bndbox>
      <xmin>230</xmin>
      <ymin>89</ymin>
      <xmax>324</xmax>
      <ymax>184</ymax>
    </bndbox>
  </object>
  <object>
    <name>TextView</name>
    <pose>Unspecified</pose>
    <truncated>0</truncated>
    <difficult>0</difficult>
    <bndbox>
      <xmin>324</xmin>
      <ymin>108</ymin>
      <xmax>838</xmax>
      <ymax>165</ymax>
    </bndbox>
  </object>
  <object>
    <name>TextView</name>
    <pose>Unspecified</pose>
    <truncated>0</truncated>
    <difficult>0</difficult>
    <bndbox>
      <xmin>838</xmin>
      <ymin>63</ymin>
      <xmax>959</xmax>
      <ymax>210</ymax>
    </bndbox>
  </object>
  <object>
    <name>TextView</name>
    <pose>Unspecified</pose>
    <truncated>0</truncated>
    <difficult>0</difficult>
    <bndbox>
      <xmin>959</xmin>
      <ymin>63</ymin>
      <xmax>1080</xmax>
      <ymax>210</ymax>
    </bndbox>
  </object>
  <object>
    <name>Layout</name>
    <pose>Unspecified</pose>
    <truncated>0</truncated>
    <difficult>0</difficult>
    <bndbox>
      <xmin>188</xmin>
      <ymin>210</ymin>
      <xmax>1080</xmax>
      <ymax>357</ymax>
    </bndbox>
  </object>
  <object>
    <name>View</name>
    <pose>Unspecified</pose>
    <truncated>0</truncated>
    <difficult>0</difficult>
    <bndbox>
      <xmin>188</xmin>
      <ymin>210</ymin>
      <xmax>484</xmax>
      <ymax>357</ymax>
    </bndbox>
  </object>
  <object>
    <name>TextView</name>
    <pose>Unspecified</pose>
    <truncated>0</truncated>
    <difficult>0</difficult>
    <bndbox>
      <xmin>219</xmin>
      <ymin>259</ymin>
      <xmax>453</xmax>
      <ymax>308</ymax>
    </bndbox>
  </object>
  <object>
    <name>Pager</name>
    <pose>Unspecified</pose>
    <truncated>0</truncated>
    <difficult>0</difficult>
    <bndbox>
      <xmin>188</xmin>
      <ymin>360</ymin>
      <xmax>1080</xmax>
      <ymax>1794</ymax>
    </bndbox>
  </object>
  <object>
    <name>View</name>
    <pose>Unspecified</pose>
    <truncated>0</truncated>
    <difficult>0</difficult>
    <bndbox>
      <xmin>188</xmin>
      <ymin>360</ymin>
      <xmax>1080</xmax>
      <ymax>1794</ymax>
    </bndbox>
  </object>
  <object>
    <name>TextView</name>
    <pose>Unspecified</pose>
    <truncated>0</truncated>
    <difficult>0</difficult>
    <bndbox>
      <xmin>555</xmin>
      <ymin>518</ymin>
      <xmax>712</xmax>
      <ymax>691</ymax>
    </bndbox>
  </object>
  <object>
    <name>TextView</name>
    <pose>Unspecified</pose>
    <truncated>0</truncated>
    <difficult>0</difficult>
    <bndbox>
      <xmin>260</xmin>
      <ymin>722</ymin>
      <xmax>1007</xmax>
      <ymax>779</ymax>
    </bndbox>
  </object>
  <object>
    <name>LinearLayout</name>
    <pose>Unspecified</pose>
    <truncated>0</truncated>
    <difficult>0</difficult>
    <bndbox>
      <xmin>0</xmin>
      <ymin>63</ymin>
      <xmax>188</xmax>
      <ymax>1794</ymax>
    </bndbox>
  </object>
  <object>
    <name>FrameLayout</name>
    <pose>Unspecified</pose>
    <truncated>0</truncated>
    <difficult>0</difficult>
    <bndbox>
      <xmin>0</xmin>
      <ymin>63</ymin>
      <xmax>188</xmax>
      <ymax>1794</ymax>
    </bndbox>
  </object>
  <object>
    <name>Bar</name>
    <pose>Unspecified</pose>
    <truncated>0</truncated>
    <difficult>0</difficult>
    <bndbox>
      <xmin>0</xmin>
      <ymin>63</ymin>
      <xmax>188</xmax>
      <ymax>210</ymax>
    </bndbox>
  </object>
  <object>
    <name>View</name>
    <pose>Unspecified</pose>
    <truncated>0</truncated>
    <difficult>0</difficult>
    <bndbox>
      <xmin>0</xmin>
      <ymin>86</ymin>
      <xmax>62</xmax>
      <ymax>186</ymax>
    </bndbox>
  </object>
  <object>
    <name>Pager</name>
    <pose>Unspecified</pose>
    <truncated>0</truncated>
    <difficult>0</difficult>
    <bndbox>
      <xmin>0</xmin>
      <ymin>210</ymin>
      <xmax>188</xmax>
      <ymax>1794</ymax>
    </bndbox>
  </object>
  <object>
    <name>View</name>
    <pose>Unspecified</pose>
    <truncated>0</truncated>
    <difficult>0</difficult>
    <bndbox>
      <xmin>0</xmin>
      <ymin>210</ymin>
      <xmax>188</xmax>
      <ymax>1794</ymax>
    </bndbox>
  </object>
  <object>
    <name>ImageView</name>
    <pose>Unspecified</pose>
    <truncated>0</truncated>
    <difficult>0</difficult>
    <bndbox>
      <xmin>0</xmin>
      <ymin>210</ymin>
      <xmax>188</xmax>
      <ymax>630</ymax>
    </bndbox>
  </object>
  <object>
    <name>View</name>
    <pose>Unspecified</pose>
    <truncated>0</truncated>
    <difficult>0</difficult>
    <bndbox>
      <xmin>0</xmin>
      <ymin>210</ymin>
      <xmax>188</xmax>
      <ymax>226</ymax>
    </bndbox>
  </object>
</annotation>
