<annotation>
  <folder>VOC2007</folder>
  <filename>000450.jpg</filename>
  <size>
    <width>1080</width>
    <height>1920</height>
    <depth>3</depth>
  </size>
  <object>
    <name>Bar</name>
    <pose>Unspecified</pose>
    <truncated>0</truncated>
    <difficult>0</difficult>
    <bndbox>
      <xmin>5</xmin>
      <ymin>63</ymin>
      <xmax>1075</xmax>
      <ymax>210</ymax>
    </bndbox>
  </object>
  <object>
    <name>ImageView</name>
    <pose>Unspecified</pose>
    <truncated>0</truncated>
    <difficult>0</difficult>
    <bndbox>
      <xmin>828</xmin>
      <ymin>74</ymin>
      <xmax>954</xmax>
      <ymax>200</ymax>
    </bndbox>
  </object>
  <object>
    <name>Bar</name>
    <pose>Unspecified</pose>
    <truncated>0</truncated>
    <difficult>0</difficult>
    <bndbox>
      <xmin>477</xmin>
      <ymin>866</ymin>
      <xmax>603</xmax>
      <ymax>991</ymax>
    </bndbox>
  </object>
  <object>
    <name>ImageView</name>
    <pose>Unspecified</pose>
    <truncated>0</truncated>
    <difficult>0</difficult>
    <bndbox>
      <xmin>398</xmin>
      <ymin>548</ymin>
      <xmax>682</xmax>
      <ymax>831</ymax>
    </bndbox>
  </object>
  <object>
    <name>Button</name>
    <pose>Unspecified</pose>
    <truncated>0</truncated>
    <difficult>0</difficult>
    <bndbox>
      <xmin>404</xmin>
      <ymin>1175</ymin>
      <xmax>676</xmax>
      <ymax>1309</ymax>
    </bndbox>
  </object>
  <object>
    <name>Bar</name>
    <pose>Unspecified</pose>
    <truncated>0</truncated>
    <difficult>0</difficult>
    <bndbox>
      <xmin>5</xmin>
      <ymin>1647</ymin>
      <xmax>1075</xmax>
      <ymax>1794</ymax>
    </bndbox>
  </object>
  <object>
    <name>ImageView</name>
    <pose>Unspecified</pose>
    <truncated>0</truncated>
    <difficult>0</difficult>
    <bndbox>
      <xmin>57</xmin>
      <ymin>1647</ymin>
      <xmax>120</xmax>
      <ymax>1752</ymax>
    </bndbox>
  </object>
</annotation>
